<?xml version="1.0" encoding="UTF-8" ?>
<!DOCTYPE mapper PUBLIC "-//mybatis.org//DTD Mapper 3.0//EN" "http://mybatis.org/dtd/mybatis-3-mapper.dtd" >
<mapper namespace="com.ecnu.car_rent.dao.MassageMapper" >
  <resultMap id="BaseResultMap" type="com.ecnu.car_rent.model.Massage" >
    <!--
      WARNING - @mbggenerated
      This element is automatically generated by MyBatis Generator, do not modify.
      This element was generated on Tue Dec 19 14:39:15 CST 2017.
    -->
    <constructor >
      <idArg column="massage_id" jdbcType="INTEGER" javaType="java.lang.Integer" />
      <arg column="car_order_id" jdbcType="INTEGER" javaType="java.lang.Integer" />
      <arg column="sender_name" jdbcType="VARCHAR" javaType="java.lang.String" />
      <arg column="date" jdbcType="TIMESTAMP" javaType="java.util.Date" />
    </constructor>
  </resultMap>
  <resultMap id="ResultMapWithBLOBs" type="com.ecnu.car_rent.model.Massage" >
    <!--
      WARNING - @mbggenerated
      This element is automatically generated by MyBatis Generator, do not modify.
      This element was generated on Tue Dec 19 14:39:15 CST 2017.
    -->
    <constructor >
      <idArg column="massage_id" jdbcType="INTEGER" javaType="java.lang.Integer" />
      <arg column="car_order_id" jdbcType="INTEGER" javaType="java.lang.Integer" />
      <arg column="sender_name" jdbcType="VARCHAR" javaType="java.lang.String" />
      <arg column="date" jdbcType="TIMESTAMP" javaType="java.util.Date" />
      <arg column="text" jdbcType="LONGVARCHAR" javaType="java.lang.String" />
    </constructor>
  </resultMap>
  <sql id="Base_Column_List" >
    <!--
      WARNING - @mbggenerated
      This element is automatically generated by MyBatis Generator, do not modify.
      This element was generated on Tue Dec 19 14:39:15 CST 2017.
    -->
    massage_id, car_order_id, sender_name, date
  </sql>
  <sql id="Blob_Column_List" >
    <!--
      WARNING - @mbggenerated
      This element is automatically generated by MyBatis Generator, do not modify.
      This element was generated on Tue Dec 19 14:39:15 CST 2017.
    -->
    text
  </sql>

  <select id="selectAllMassagesByCarOrderId" resultMap="ResultMapWithBLOBs" parameterType="java.lang.Integer">
    <!--
      倪事通
    -->
    select
    <include refid="Base_Column_List"/>
    ,
    <include refid="Blob_Column_List"/>
    from massage
    where car_order_id = #{id,jdbcType=INTEGER}
    ORDER BY massage_id
  </select>
  <select id="selectAllMassages" resultMap="ResultMapWithBLOBs">
    <!--
      倪事通
    -->
    select
    <include refid="Base_Column_List"/>
    ,
    <include refid="Blob_Column_List"/>
    from massage
    ORDER BY massage_id
  </select>
  <select id="selectAllMassagesBySenderName" resultMap="ResultMapWithBLOBs" parameterType="java.lang.String">
    <!--
      倪事通
    -->
    select
    <include refid="Base_Column_List"/>
    ,
    <include refid="Blob_Column_List"/>
    from massage
    WHERE sender_name = #{senderName,jdbcType=VARCHAR}
    ORDER BY massage_id
  </select>

  <select id="selectByPrimaryKey" resultMap="ResultMapWithBLOBs" parameterType="java.lang.Integer" >
    <!--
      WARNING - @mbggenerated
      This element is automatically generated by MyBatis Generator, do not modify.
      This element was generated on Tue Dec 19 14:39:15 CST 2017.
    -->
    select 
    <include refid="Base_Column_List" />
    ,
    <include refid="Blob_Column_List" />
    from massage
    where massage_id = #{massageId,jdbcType=INTEGER}
  </select>
  <delete id="deleteByPrimaryKey" parameterType="java.lang.Integer" >
    <!--
      WARNING - @mbggenerated
      This element is automatically generated by MyBatis Generator, do not modify.
      This element was generated on Tue Dec 19 14:39:15 CST 2017.
    -->
    delete from massage
    where massage_id = #{massageId,jdbcType=INTEGER}
  </delete>
  <insert id="insert" parameterType="com.ecnu.car_rent.model.Massage" >
    <!--
      WARNING - @mbggenerated
      This element is automatically generated by MyBatis Generator, do not modify.
      This element was generated on Tue Dec 19 14:39:15 CST 2017.
    -->
    insert into massage (massage_id, car_order_id, sender_name, 
      date, text)
    values (#{massageId,jdbcType=INTEGER}, #{carOrderId,jdbcType=INTEGER}, #{senderName,jdbcType=VARCHAR}, 
      #{date,jdbcType=TIMESTAMP}, #{text,jdbcType=LONGVARCHAR})
  </insert>
  <insert id="insertSelective" parameterType="com.ecnu.car_rent.model.Massage" >
    <!--
      WARNING - @mbggenerated
      This element is automatically generated by MyBatis Generator, do not modify.
      This element was generated on Tue Dec 19 14:39:15 CST 2017.
    -->
    insert into massage
    <trim prefix="(" suffix=")" suffixOverrides="," >
      <if test="massageId != null" >
        massage_id,
      </if>
      <if test="carOrderId != null" >
        car_order_id,
      </if>
      <if test="senderName != null" >
        sender_name,
      </if>
      <if test="date != null" >
        date,
      </if>
      <if test="text != null" >
        text,
      </if>
    </trim>
    <trim prefix="values (" suffix=")" suffixOverrides="," >
      <if test="massageId != null" >
        #{massageId,jdbcType=INTEGER},
      </if>
      <if test="carOrderId != null" >
        #{carOrderId,jdbcType=INTEGER},
      </if>
      <if test="senderName != null" >
        #{senderName,jdbcType=VARCHAR},
      </if>
      <if test="date != null" >
        #{date,jdbcType=TIMESTAMP},
      </if>
      <if test="text != null" >
        #{text,jdbcType=LONGVARCHAR},
      </if>
    </trim>
  </insert>
  <update id="updateByPrimaryKeySelective" parameterType="com.ecnu.car_rent.model.Massage" >
    <!--
      WARNING - @mbggenerated
      This element is automatically generated by MyBatis Generator, do not modify.
      This element was generated on Tue Dec 19 14:39:15 CST 2017.
    -->
    update massage
    <set >
      <if test="carOrderId != null" >
        car_order_id = #{carOrderId,jdbcType=INTEGER},
      </if>
      <if test="senderName != null" >
        sender_name = #{senderName,jdbcType=VARCHAR},
      </if>
      <if test="date != null" >
        date = #{date,jdbcType=TIMESTAMP},
      </if>
      <if test="text != null" >
        text = #{text,jdbcType=LONGVARCHAR},
      </if>
    </set>
    where massage_id = #{massageId,jdbcType=INTEGER}
  </update>
  <update id="updateByPrimaryKeyWithBLOBs" parameterType="com.ecnu.car_rent.model.Massage" >
    <!--
      WARNING - @mbggenerated
      This element is automatically generated by MyBatis Generator, do not modify.
      This element was generated on Tue Dec 19 14:39:15 CST 2017.
    -->
    update massage
    set car_order_id = #{carOrderId,jdbcType=INTEGER},
      sender_name = #{senderName,jdbcType=VARCHAR},
      date = #{date,jdbcType=TIMESTAMP},
      text = #{text,jdbcType=LONGVARCHAR}
    where massage_id = #{massageId,jdbcType=INTEGER}
  </update>
  <update id="updateByPrimaryKey" parameterType="com.ecnu.car_rent.model.Massage" >
    <!--
      WARNING - @mbggenerated
      This element is automatically generated by MyBatis Generator, do not modify.
      This element was generated on Tue Dec 19 14:39:15 CST 2017.
    -->
    update massage
    set car_order_id = #{carOrderId,jdbcType=INTEGER},
      sender_name = #{senderName,jdbcType=VARCHAR},
      date = #{date,jdbcType=TIMESTAMP}
    where massage_id = #{massageId,jdbcType=INTEGER}
  </update>
</mapper>